{"1241021": "Peix\u00e3o Irado", "1893918": "Christimao", "1245808": "Diego Pereira FC", "8912058": "Markitos Bar", "1889674": "0VINTE1 FC", "13957925": "oSantista", "71375": "Denoris F.C.", "48733": "Ra\u00e7a Tim\u00e3o!!!", "3646412": "Gabitreta F C", "219929": "Camisa21FC", "1235701": "Eae Malandro FC", "25582672": "JevyGoal", "25588958": "JUNA FUTEBOL CLUBE", "315637": "Real Beach Soccer", "18796615": "Golden Lions FC", "19190102": "ThiagoRolo FC", "579336": "CFDS06", "44514741": "Rod Santos FC", "44509672": "FAFA SHOW FC", "14439636": "ArrascaMaisDez", "279314": "AvantiHulkFc", "28919430": "Gonella Verde ", "19317259": "Xanpion", "44558779": "S\u00f3h Taapa FC", "977136": "RIVA 77 "}