{"Cap\u00edtulo4 Vers\u00edculo3": [{"I": 10, "PP": 0, "PC": 0, "FC": 47, "CA": 8, "CV": 0, "GC": 0, "GS": 3, "G": 9, "A": 6, "FT": 2, "FD": 22, "FF": 22, "FS": 46, "PS": 1, "DS": 42, "SG": 8, "DE": 12, "DP": 0, "V": 2}, " ", {"I": "-1.00", "PP": "0.00", "PC": "0.00", "FC": "-14.10", "CA": "-8.00", "CV": "0.00", "GC": "0.00", "GS": "-3.00", "G": "72.00", "A": "30.00", "FT": "6.00", "FD": "26.40", "FF": "17.60", "FS": "23.00", "PS": "1.00", "DS": "50.40", "SG": "40.00", "DE": "12.00", "DP": "0.00", "V": "2.00"}], "Denoris F.C.": [{"I": 9, "PP": 0, "PC": 0, "FC": 54, "CA": 10, "CV": 0, "GC": 1, "GS": 4, "G": 10, "A": 5, "FT": 1, "FD": 24, "FF": 31, "FS": 51, "PS": 0, "DS": 40, "SG": 6, "DE": 12, "DP": 0, "V": 3}, " ", {"I": "-0.90", "PP": "0.00", "PC": "0.00", "FC": "-16.20", "CA": "-10.00", "CV": "0.00", "GC": "-3.00", "GS": "-4.00", "G": "80.00", "A": "25.00", "FT": "3.00", "FD": "28.80", "FF": "24.80", "FS": "25.50", "PS": "0.00", "DS": "48.00", "SG": "30.00", "DE": "12.00", "DP": "0.00", "V": "3.00"}], "0VINTE1 FC": [{"I": 7, "PP": 0, "PC": 0, "FC": 47, "CA": 6, "CV": 0, "GC": 0, "GS": 3, "G": 6, "A": 5, "FT": 1, "FD": 22, "FF": 28, "FS": 53, "PS": 1, "DS": 54, "SG": 9, "DE": 11, "DP": 0, "V": 1}, " ", {"I": "-0.70", "PP": "0.00", "PC": "0.00", "FC": "-14.10", "CA": "-6.00", "CV": "0.00", "GC": "0.00", "GS": "-3.00", "G": "48.00", "A": "25.00", "FT": "3.00", "FD": "26.40", "FF": "22.40", "FS": "26.50", "PS": "1.00", "DS": "64.80", "SG": "45.00", "DE": "11.00", "DP": "0.00", "V": "1.00"}], "FAFA SHOW FC": [{"I": 8, "PP": 0, "PC": 0, "FC": 51, "CA": 3, "CV": 0, "GC": 0, "GS": 4, "G": 5, "A": 4, "FT": 2, "FD": 26, "FF": 31, "FS": 51, "PS": 1, "DS": 57, "SG": 8, "DE": 10, "DP": 0, "V": 1}, " ", {"I": "-0.80", "PP": "0.00", "PC": "0.00", "FC": "-15.30", "CA": "-3.00", "CV": "0.00", "GC": "0.00", "GS": "-4.00", "G": "40.00", "A": "20.00", "FT": "6.00", "FD": "31.20", "FF": "24.80", "FS": "25.50", "PS": "1.00", "DS": "68.40", "SG": "40.00", "DE": "10.00", "DP": "0.00", "V": "1.00"}], "Contra Tudo e Todos Avanti!": [{"I": 11, "PP": 0, "PC": 0, "FC": 51, "CA": 10, "CV": 0, "GC": 0, "GS": 1, "G": 6, "A": 5, "FT": 3, "FD": 25, "FF": 24, "FS": 43, "PS": 1, "DS": 40, "SG": 8, "DE": 18, "DP": 0, "V": 2}, " ", {"I": "-1.10", "PP": "0.00", "PC": "0.00", "FC": "-15.30", "CA": "-10.00", "CV": "0.00", "GC": "0.00", "GS": "-1.00", "G": "48.00", "A": "25.00", "FT": "9.00", "FD": "30.00", "FF": "19.20", "FS": "21.50", "PS": "1.00", "DS": "48.00", "SG": "40.00", "DE": "18.00", "DP": "0.00", "V": "2.00"}], "Ra\u00e7a Tim\u00e3o!!!": [{"I": 7, "PP": 0, "PC": 0, "FC": 46, "CA": 8, "CV": 0, "GC": 0, "GS": 4, "G": 8, "A": 2, "FT": 1, "FD": 22, "FF": 28, "FS": 47, "PS": 1, "DS": 50, "SG": 8, "DE": 15, "DP": 0, "V": 2}, " ", {"I": "-0.70", "PP": "0.00", "PC": "0.00", "FC": "-13.80", "CA": "-8.00", "CV": "0.00", "GC": "0.00", "GS": "-4.00", "G": "64.00", "A": "10.00", "FT": "3.00", "FD": "26.40", "FF": "22.40", "FS": "23.50", "PS": "1.00", "DS": "60.00", "SG": "40.00", "DE": "15.00", "DP": "0.00", "V": "2.00"}], "oSantista": [{"I": 7, "PP": 0, "PC": 0, "FC": 43, "CA": 8, "CV": 0, "GC": 0, "GS": 5, "G": 7, "A": 5, "FT": 2, "FD": 19, "FF": 26, "FS": 53, "PS": 1, "DS": 48, "SG": 6, "DE": 13, "DP": 0, "V": 1}, " ", {"I": "-0.70", "PP": "0.00", "PC": "0.00", "FC": "-12.90", "CA": "-8.00", "CV": "0.00", "GC": "0.00", "GS": "-5.00", "G": "56.00", "A": "25.00", "FT": "6.00", "FD": "22.80", "FF": "20.80", "FS": "26.50", "PS": "1.00", "DS": "57.60", "SG": "30.00", "DE": "13.00", "DP": "0.00", "V": "1.00"}], "RR Football Club": [{"I": 9, "PP": 0, "PC": 0, "FC": 47, "CA": 5, "CV": 0, "GC": 0, "GS": 5, "G": 6, "A": 3, "FT": 2, "FD": 22, "FF": 28, "FS": 49, "PS": 1, "DS": 43, "SG": 8, "DE": 17, "DP": 0, "V": 2}, " ", {"I": "-0.90", "PP": "0.00", "PC": "0.00", "FC": "-14.10", "CA": "-5.00", "CV": "0.00", "GC": "0.00", "GS": "-5.00", "G": "48.00", "A": "15.00", "FT": "6.00", "FD": "26.40", "FF": "22.40", "FS": "24.50", "PS": "1.00", "DS": "51.60", "SG": "40.00", "DE": "17.00", "DP": "0.00", "V": "2.00"}], "Diego Pereira FC": [{"I": 8, "PP": 0, "PC": 0, "FC": 47, "CA": 9, "CV": 0, "GC": 0, "GS": 3, "G": 6, "A": 3, "FT": 1, "FD": 22, "FF": 32, "FS": 50, "PS": 0, "DS": 48, "SG": 8, "DE": 12, "DP": 0, "V": 2}, " ", {"I": "-0.80", "PP": "0.00", "PC": "0.00", "FC": "-14.10", "CA": "-9.00", "CV": "0.00", "GC": "0.00", "GS": "-3.00", "G": "48.00", "A": "15.00", "FT": "3.00", "FD": "26.40", "FF": "25.60", "FS": "25.00", "PS": "0.00", "DS": "57.60", "SG": "40.00", "DE": "12.00", "DP": "0.00", "V": "2.00"}], "S\u00f3h Taapa FC": [{"I": 7, "PP": 0, "PC": 0, "FC": 47, "CA": 9, "CV": 0, "GC": 0, "GS": 4, "G": 7, "A": 3, "FT": 1, "FD": 23, "FF": 24, "FS": 48, "PS": 1, "DS": 50, "SG": 6, "DE": 12, "DP": 0, "V": 1}, " ", {"I": "-0.70", "PP": "0.00", "PC": "0.00", "FC": "-14.10", "CA": "-9.00", "CV": "0.00", "GC": "0.00", "GS": "-4.00", "G": "56.00", "A": "15.00", "FT": "3.00", "FD": "27.60", "FF": "19.20", "FS": "24.00", "PS": "1.00", "DS": "60.00", "SG": "30.00", "DE": "12.00", "DP": "0.00", "V": "1.00"}], "Christimao": [{"I": 8, "PP": 0, "PC": 1, "FC": 53, "CA": 10, "CV": 2, "GC": 0, "GS": 3, "G": 6, "A": 1, "FT": 1, "FD": 31, "FF": 29, "FS": 50, "PS": 0, "DS": 44, "SG": 7, "DE": 18, "DP": 0, "V": 2}, " ", {"I": "-0.80", "PP": "0.00", "PC": "-1.00", "FC": "-15.90", "CA": "-10.00", "CV": "-6.00", "GC": "0.00", "GS": "-3.00", "G": "48.00", "A": "5.00", "FT": "3.00", "FD": "37.20", "FF": "23.20", "FS": "25.00", "PS": "0.00", "DS": "52.80", "SG": "35.00", "DE": "18.00", "DP": "0.00", "V": "2.00"}], "Real Beach Soccer": [{"I": 9, "PP": 0, "PC": 0, "FC": 52, "CA": 6, "CV": 0, "GC": 0, "GS": 7, "G": 5, "A": 5, "FT": 3, "FD": 24, "FF": 23, "FS": 40, "PS": 1, "DS": 39, "SG": 5, "DE": 19, "DP": 0, "V": 3}, " ", {"I": "-0.90", "PP": "0.00", "PC": "0.00", "FC": "-15.60", "CA": "-6.00", "CV": "0.00", "GC": "0.00", "GS": "-7.00", "G": "40.00", "A": "25.00", "FT": "9.00", "FD": "28.80", "FF": "18.40", "FS": "20.00", "PS": "1.00", "DS": "46.80", "SG": "25.00", "DE": "19.00", "DP": "0.00", "V": "3.00"}], "Gonella Verde ": [{"I": 10, "PP": 0, "PC": 0, "FC": 53, "CA": 9, "CV": 0, "GC": 0, "GS": 5, "G": 7, "A": 2, "FT": 1, "FD": 22, "FF": 23, "FS": 37, "PS": 1, "DS": 46, "SG": 5, "DE": 13, "DP": 0, "V": 2}, " ", {"I": "-1.00", "PP": "0.00", "PC": "0.00", "FC": "-15.90", "CA": "-9.00", "CV": "0.00", "GC": "0.00", "GS": "-5.00", "G": "56.00", "A": "10.00", "FT": "3.00", "FD": "26.40", "FF": "18.40", "FS": "18.50", "PS": "1.00", "DS": "55.20", "SG": "25.00", "DE": "13.00", "DP": "0.00", "V": "2.00"}], "JevyGoal FC": [{"I": 8, "PP": 1, "PC": 1, "FC": 41, "CA": 8, "CV": 0, "GC": 1, "GS": 4, "G": 3, "A": 7, "FT": 1, "FD": 27, "FF": 18, "FS": 53, "PS": 0, "DS": 44, "SG": 5, "DE": 13, "DP": 0, "V": 1}, " ", {"I": "-0.80", "PP": "-4.00", "PC": "-1.00", "FC": "-12.30", "CA": "-8.00", "CV": "0.00", "GC": "-3.00", "GS": "-4.00", "G": "24.00", "A": "35.00", "FT": "3.00", "FD": "32.40", "FF": "14.40", "FS": "26.50", "PS": "0.00", "DS": "52.80", "SG": "25.00", "DE": "13.00", "DP": "0.00", "V": "1.00"}], "Peix\u00e3o Irado": [{"I": 7, "PP": 0, "PC": 0, "FC": 63, "CA": 13, "CV": 1, "GC": 0, "GS": 3, "G": 7, "A": 3, "FT": 0, "FD": 19, "FF": 22, "FS": 46, "PS": 1, "DS": 46, "SG": 6, "DE": 11, "DP": 0, "V": 1}, " ", {"I": "-0.70", "PP": "0.00", "PC": "0.00", "FC": "-18.90", "CA": "-13.00", "CV": "-3.00", "GC": "0.00", "GS": "-3.00", "G": "56.00", "A": "15.00", "FT": "0.00", "FD": "22.80", "FF": "17.60", "FS": "23.00", "PS": "1.00", "DS": "55.20", "SG": "30.00", "DE": "11.00", "DP": "0.00", "V": "1.00"}], "Markitos Bar": [{"I": 7, "PP": 0, "PC": 1, "FC": 45, "CA": 9, "CV": 0, "GC": 0, "GS": 3, "G": 4, "A": 3, "FT": 1, "FD": 19, "FF": 20, "FS": 48, "PS": 0, "DS": 32, "SG": 8, "DE": 19, "DP": 0, "V": 2}, " ", {"I": "-0.70", "PP": "0.00", "PC": "-1.00", "FC": "-13.50", "CA": "-9.00", "CV": "0.00", "GC": "0.00", "GS": "-3.00", "G": "32.00", "A": "15.00", "FT": "3.00", "FD": "22.80", "FF": "16.00", "FS": "24.00", "PS": "0.00", "DS": "38.40", "SG": "40.00", "DE": "19.00", "DP": "0.00", "V": "2.00"}], "RIVA 77 ": [{"I": 8, "PP": 0, "PC": 0, "FC": 46, "CA": 10, "CV": 0, "GC": 0, "GS": 6, "G": 6, "A": 5, "FT": 2, "FD": 17, "FF": 24, "FS": 40, "PS": 0, "DS": 32, "SG": 4, "DE": 16, "DP": 0, "V": 1}, " ", {"I": "-0.80", "PP": "0.00", "PC": "0.00", "FC": "-13.80", "CA": "-10.00", "CV": "0.00", "GC": "0.00", "GS": "-6.00", "G": "48.00", "A": "25.00", "FT": "6.00", "FD": "20.40", "FF": "19.20", "FS": "20.00", "PS": "0.00", "DS": "38.40", "SG": "20.00", "DE": "16.00", "DP": "0.00", "V": "1.00"}], "Camisa21FC": [{"I": 6, "PP": 0, "PC": 0, "FC": 47, "CA": 9, "CV": 0, "GC": 0, "GS": 5, "G": 6, "A": 2, "FT": 2, "FD": 20, "FF": 20, "FS": 51, "PS": 0, "DS": 37, "SG": 5, "DE": 13, "DP": 0, "V": 1}, " ", {"I": "-0.60", "PP": "0.00", "PC": "0.00", "FC": "-14.10", "CA": "-9.00", "CV": "0.00", "GC": "0.00", "GS": "-5.00", "G": "48.00", "A": "10.00", "FT": "6.00", "FD": "24.00", "FF": "16.00", "FS": "25.50", "PS": "0.00", "DS": "44.40", "SG": "25.00", "DE": "13.00", "DP": "0.00", "V": "1.00"}], "ThiagoRolo FC": [{"I": 2, "PP": 0, "PC": 0, "FC": 51, "CA": 10, "CV": 0, "GC": 0, "GS": 6, "G": 6, "A": 2, "FT": 2, "FD": 13, "FF": 16, "FS": 41, "PS": 0, "DS": 65, "SG": 4, "DE": 7, "DP": 0, "V": 1}, " ", {"I": "-0.20", "PP": "0.00", "PC": "0.00", "FC": "-15.30", "CA": "-10.00", "CV": "0.00", "GC": "0.00", "GS": "-6.00", "G": "48.00", "A": "10.00", "FT": "6.00", "FD": "15.60", "FF": "12.80", "FS": "20.50", "PS": "0.00", "DS": "78.00", "SG": "20.00", "DE": "7.00", "DP": "0.00", "V": "1.00"}], "Gabitreta F C": [{"I": 6, "PP": 0, "PC": 0, "FC": 60, "CA": 7, "CV": 0, "GC": 0, "GS": 9, "G": 5, "A": 3, "FT": 0, "FD": 16, "FF": 18, "FS": 32, "PS": 1, "DS": 49, "SG": 6, "DE": 10, "DP": 0, "V": 4}, " ", {"I": "-0.60", "PP": "0.00", "PC": "0.00", "FC": "-18.00", "CA": "-7.00", "CV": "0.00", "GC": "0.00", "GS": "-9.00", "G": "40.00", "A": "15.00", "FT": "0.00", "FD": "19.20", "FF": "14.40", "FS": "16.00", "PS": "1.00", "DS": "58.80", "SG": "30.00", "DE": "10.00", "DP": "0.00", "V": "4.00"}], "Eae Malandro FC": [{"I": 9, "PP": 0, "PC": 0, "FC": 56, "CA": 8, "CV": 0, "GC": 0, "GS": 7, "G": 4, "A": 3, "FT": 1, "FD": 16, "FF": 19, "FS": 38, "PS": 0, "DS": 46, "SG": 4, "DE": 12, "DP": 0, "V": 1}, " ", {"I": "-0.90", "PP": "0.00", "PC": "0.00", "FC": "-16.80", "CA": "-8.00", "CV": "0.00", "GC": "0.00", "GS": "-7.00", "G": "32.00", "A": "15.00", "FT": "3.00", "FD": "19.20", "FF": "15.20", "FS": "19.00", "PS": "0.00", "DS": "55.20", "SG": "20.00", "DE": "12.00", "DP": "0.00", "V": "1.00"}], "Santa Cruz Bahamas FC": [{"I": 4, "PP": 0, "PC": 0, "FC": 44, "CA": 7, "CV": 1, "GC": 1, "GS": 2, "G": 3, "A": 5, "FT": 0, "FD": 12, "FF": 14, "FS": 33, "PS": 0, "DS": 39, "SG": 6, "DE": 14, "DP": 0, "V": 0}, " ", {"I": "-0.40", "PP": "0.00", "PC": "0.00", "FC": "-13.20", "CA": "-7.00", "CV": "-3.00", "GC": "-3.00", "GS": "-2.00", "G": "24.00", "A": "25.00", "FT": "0.00", "FD": "14.40", "FF": "11.20", "FS": "16.50", "PS": "0.00", "DS": "46.80", "SG": "30.00", "DE": "14.00", "DP": "0.00", "V": "0.00"}]}